flask_ponywhoosh/__init__.py
flask_ponywhoosh/form.py
flask_ponywhoosh/views.py
flask_ponywhoosh/templates/ponywhoosh/base.html
flask_ponywhoosh/templates/ponywhoosh/index.html
flask_ponywhoosh/templates/ponywhoosh/results.html
flask_ponywhoosh-1.0.9.dist-info/DESCRIPTION.rst
flask_ponywhoosh-1.0.9.dist-info/METADATA
flask_ponywhoosh-1.0.9.dist-info/RECORD
flask_ponywhoosh-1.0.9.dist-info/WHEEL
flask_ponywhoosh-1.0.9.dist-info/metadata.json
flask_ponywhoosh-1.0.9.dist-info/top_level.txt
