Metadata-Version: 2.0
Name: flask-ponywhoosh
Version: 1.0.9
Summary: A search engine for Flask using Pony ORM and Whoosh.
Home-page: https://github.com/jonaprieto/flask-ponywhoosh
Author: Jonathan Prieto-Cubides & Felipe Rodriguez
Author-email: jprieto9@eafit.edu.co
License: MIT
Keywords: elastic,engine,flask,flask-sqlalchemy,flask-whooshalchemy,mysql,pony,ponyorm,ponywhoosh,search,searchengine,searchable,sqlite3,whoosh
Platform: any
Classifier: Environment :: Web Environment
Classifier: Intended Audience :: Developers
Classifier: License :: OSI Approved :: MIT License
Classifier: Operating System :: OS Independent
Classifier: Programming Language :: Python
Classifier: Topic :: Internet :: WWW/HTTP :: Dynamic Content
Classifier: Topic :: Software Development :: Libraries :: Python Modules
Requires-Dist: flask-bootstrap
Requires-Dist: flask-wtf
Requires-Dist: ponywhoosh
Requires-Dist: flask
Requires-Dist: flask-script
